{
  "id": "chaos_nova",
  "category": "Upgrade",
  "related_skill": "abyss_knight",
  "damage_type": "Weapon Damage",
  "description": [
    "Knights proc a deadly nova on kill and when killed",
    "130% Weapon Damage"
  ],
  "synergies": [
    "0.5% chance to cast Chaos Nova on Kill per base level",
    "10% chance to cast Chaos Nova on Death per base level"
  ],
  "scaling": [
    { "level": 1, "cast_on_kill": 0, "cast_on_death": 10 },
    { "level": 2, "cast_on_kill": 1, "cast_on_death": 20 },
    { "level": 3, "cast_on_kill": 1, "cast_on_death": 30 },
    { "level": 4, "cast_on_kill": 2, "cast_on_death": 40 },
    { "level": 5, "cast_on_kill": 2, "cast_on_death": 50 },
    { "level": 6, "cast_on_kill": 3, "cast_on_death": 60 },
    { "level": 7, "cast_on_kill": 3, "cast_on_death": 70 },
    { "level": 8, "cast_on_kill": 4, "cast_on_death": 80 },
    { "level": 9, "cast_on_kill": 4, "cast_on_death": 90 },
    { "level": 10, "cast_on_kill": 5, "cast_on_death": 100 }
  ]
}